bbbrisk/__init__.py
bbbrisk/assist/__init__.py
bbbrisk/assist/_eda.py
bbbrisk/assist/_eval_effect.py
bbbrisk/bins/Bins.py
bbbrisk/bins/__init__.py
bbbrisk/bins/batch.py
bbbrisk/bins/merge.py
bbbrisk/bins/_merge/__init__.py
bbbrisk/bins/_merge/_allEnumBin.py
bbbrisk/bins/_merge/_chi2Bin.py
bbbrisk/bins/_merge/_eDistBin.py
bbbrisk/bins/_merge/_eSampleBin.py
bbbrisk/bins/_merge/_ksBin.py
bbbrisk/bins/_merge/_treeBin.py
bbbrisk/datasets/__init__.py
bbbrisk/datasets/_load.py
bbbrisk/datasets/bloan.csv
bbbrisk/datasets/bloan_grp.csv
bbbrisk/display/__init__.py
bbbrisk/display/pd.py
bbbrisk/encode/__init__.py
bbbrisk/encode/grp.py
bbbrisk/encode/woe.py
bbbrisk/model/__init__.py
bbbrisk/model/_score_card.py
bbbrisk/report/__init__.py
bbbrisk/report/_report.py
bbbrisk-1.0.2.dist-info/LICENSE
bbbrisk-1.0.2.dist-info/METADATA
bbbrisk-1.0.2.dist-info/WHEEL
bbbrisk-1.0.2.dist-info/top_level.txt
bbbrisk-1.0.2.dist-info/RECORD
