Metadata-Version: 2.1
Name: bbbrisk
Version: 1.0.2
Summary: model for loan risk controll,i.e. score card
Home-page: https://github.com/bbbdata/bbbrisk
Author: bbbdata
Author-email: yhbbbdata@163.com
Keywords: scorecard
Classifier: Programming Language :: Python :: 3
Classifier: License :: OSI Approved :: MIT License
Requires-Python: >=3.7
License-File: LICENSE
Requires-Dist: numpy
Requires-Dist: pandas
Requires-Dist: scikit-learn>=0.18
